gui_executor/__init__.py
gui_executor/__main__.py
gui_executor/__version__.py
gui_executor/client.py
gui_executor/command.py
gui_executor/config.py
gui_executor/exec.py
gui_executor/gui.py
gui_executor/kernel.py
gui_executor/model.py
gui_executor/script_app.py
gui_executor/transforms.py
gui_executor/utils.py
gui_executor/utypes.py
gui_executor/view.py
gui_executor/icons/add.svg
gui_executor/icons/arrow-down-selected.svg
gui_executor/icons/arrow-down.svg
gui_executor/icons/arrow-up-selected.svg
gui_executor/icons/arrow-up.svg
gui_executor/icons/command.svg
gui_executor/icons/delete.svg
gui_executor/icons/filename.svg
gui_executor/icons/filepath.svg
gui_executor/icons/folder.svg
gui_executor/icons/hexapod-homing-selected.svg
gui_executor/icons/hexapod-homing.svg
gui_executor/icons/hexapod-retract-selected.svg
gui_executor/icons/hexapod-retract.svg
gui_executor/icons/processing.svg
gui_executor/icons/reload-kernel.svg
gui_executor/icons/reload.svg
gui_executor/icons/script-function-selected.svg
gui_executor/icons/script-function.svg
gui_executor/icons/script_app.svg
gui_executor/icons/stop.svg
gui_executor/icons/tasks.svg
gui_executor/icons/traffic-light-green.svg
gui_executor/icons/traffic-light-orange.svg
gui_executor/icons/traffic-light-red.svg
gui_executor-0.21.1.dist-info/METADATA
gui_executor-0.21.1.dist-info/WHEEL
gui_executor-0.21.1.dist-info/entry_points.txt
gui_executor-0.21.1.dist-info/top_level.txt
gui_executor-0.21.1.dist-info/RECORD
